sbfl/__init__.py
sbfl/__main__.py
sbfl/method_defs.py
sbfl/tcm_creator.py
coverage_sbfl-0.0.1.dist-info/METADATA
coverage_sbfl-0.0.1.dist-info/WHEEL
coverage_sbfl-0.0.1.dist-info/entry_points.txt
coverage_sbfl-0.0.1.dist-info/top_level.txt
coverage_sbfl-0.0.1.dist-info/RECORD
