Metadata-Version: 2.2
Name: coverage-sbfl
Version: 0.0.1
Summary: Collect coverage from python projects compatible with Spectrum-Based Fault Localization (SBFL)!
Author-email: Dylan Callaghan <dcallaghan@acm.org>
Project-URL: Homepage, https://github.com/DCallaz/coverage-sbfl
Project-URL: Issues, https://github.com/DCallaz/coverage-sbfl/issues
Classifier: Programming Language :: Python :: 3
Classifier: Operating System :: OS Independent
Classifier: License :: OSI Approved :: MIT License
Requires-Python: >=3.6
Requires-Dist: argcomplete
Requires-Dist: coverage
